<?xml version="1.0" encoding="utf-8"?>
<!--Detailed report on module CCCC_UseRelationship-->
<CCCC_Project>
<module_summary>
<lines_of_code value="197" level="0" />
<lines_of_code_per_member_function value="******" level="0" />
<McCabes_cyclomatic_complexity value="38" level="0" />
<McCabes_cyclomatic_complexity_per_member_function value="******" level="0" />
<lines_of_code value="40" level="0" />
<lines_of_code_per_member_function value="********" level="0" />
<lines_of_code_per_line_of_comment value="4.925" level="0" />
<McCabes_cyclomatic_complexity_per_line_of_comment value="0.950" level="0" />
<weighted_methods_per_class_unity value="8" level="0" />
<weighted_methods_per_class_visibility value="0" level="0" />
<depth_of_inheritance_tree value="0" level="0" />
<number_of_children value="0" level="0" />
<coupling_between_objects value="4" level="0" />
<IF4 value="0" level="0" />
<IF4_per_member_function value="********" level="0" />
<IF4_visible value="0" level="0" />
<IF4_visible_per_member_function value="********" level="0" />
<IF4_concrete value="0" level="0" />
<IF4_concrete_per_member_function value="********" level="0" />
</module_summary>
<module_detail>
</module_detail>
<procedural_detail>
<member_function>
<name>CCCC_UseRelationship(CCCC_Item &amp;)</name>
<extent>
<description>definition</description>
<source_reference file="./cccc/cccc_use.cc" line="30" />
</extent>
<lines_of_code value="9" level="0" />
<McCabes_cyclomatic_complexity value="0" level="0" />
<lines_of_comment value="19" level="0" />
<lines_of_code_per_line_of_comment value="------" level="0" />
<McCabes_cyclomatic_complexity_per_line_of_comment value="------" level="0" />
</member_function>
<member_function>
<name>FromFile(ifstream &amp;)</name>
<extent>
<description>definition</description>
<source_reference file="./cccc/cccc_use.cc" line="206" />
</extent>
<lines_of_code value="62" level="1" />
<McCabes_cyclomatic_complexity value="12" level="1" />
<lines_of_comment value="11" level="0" />
<lines_of_code_per_line_of_comment value="5.636" level="0" />
<McCabes_cyclomatic_complexity_per_line_of_comment value="1.091" level="0" />
</member_function>
<member_function>
<name>ToFile(ofstream &amp;)</name>
<extent>
<description>definition</description>
<source_reference file="./cccc/cccc_use.cc" line="175" />
</extent>
<lines_of_code value="25" level="0" />
<McCabes_cyclomatic_complexity value="3" level="0" />
<lines_of_comment value="0" level="0" />
<lines_of_code_per_line_of_comment value="******" level="0" />
<McCabes_cyclomatic_complexity_per_line_of_comment value="------" level="0" />
</member_function>
<member_function>
<name>add_extent(CCCC_Item &amp;)</name>
<extent>
<description>definition</description>
<source_reference file="./cccc/cccc_use.cc" line="68" />
</extent>
<lines_of_code value="38" level="1" />
<McCabes_cyclomatic_complexity value="7" level="0" />
<lines_of_comment value="10" level="0" />
<lines_of_code_per_line_of_comment value="3.800" level="0" />
<McCabes_cyclomatic_complexity_per_line_of_comment value="0.700" level="0" />
</member_function>
<member_function>
<name>client_module_ptr(CCCC_Project *)</name>
<extent>
<description>definition</description>
<source_reference file="./cccc/cccc_use.cc" line="169" />
</extent>
<lines_of_code value="4" level="0" />
<McCabes_cyclomatic_complexity value="1" level="0" />
<lines_of_comment value="0" level="0" />
<lines_of_code_per_line_of_comment value="------" level="0" />
<McCabes_cyclomatic_complexity_per_line_of_comment value="------" level="0" />
</member_function>
<member_function>
<name>get_count(const char *)</name>
<extent>
<description>definition</description>
<source_reference file="./cccc/cccc_use.cc" line="122" />
</extent>
<lines_of_code value="33" level="1" />
<McCabes_cyclomatic_complexity value="9" level="0" />
<lines_of_comment value="0" level="0" />
<lines_of_code_per_line_of_comment value="******" level="0" />
<McCabes_cyclomatic_complexity_per_line_of_comment value="******" level="0" />
</member_function>
<member_function>
<name>name(int)</name>
<extent>
<description>definition</description>
<source_reference file="./cccc/cccc_use.cc" line="40" />
</extent>
<lines_of_code value="22" level="0" />
<McCabes_cyclomatic_complexity value="5" level="0" />
<lines_of_comment value="0" level="0" />
<lines_of_code_per_line_of_comment value="******" level="0" />
<McCabes_cyclomatic_complexity_per_line_of_comment value="******" level="0" />
</member_function>
<member_function>
<name>supplier_module_ptr(CCCC_Project *)</name>
<extent>
<description>definition</description>
<source_reference file="./cccc/cccc_use.cc" line="164" />
</extent>
<lines_of_code value="4" level="0" />
<McCabes_cyclomatic_complexity value="1" level="0" />
<lines_of_comment value="0" level="0" />
<lines_of_code_per_line_of_comment value="------" level="0" />
<McCabes_cyclomatic_complexity_per_line_of_comment value="------" level="0" />
</member_function>
</procedural_detail>
<structural_detail>
<module>
<name>CCCC_UseRelationship</name>
<client_module>
</client_module>
<supplier_module>
<name>CCCC_Item</name>
<visible>true</visible>
<concrete>false</concrete>
<extent>
<description>pass by reference</description>
<source_reference file="./cccc/cccc_use.cc" line="30" />
</extent>
<extent>
<description>pass by reference</description>
<source_reference file="./cccc/cccc_use.cc" line="68" />
</extent>
<name>CCCC_Project</name>
<visible>true</visible>
<concrete>false</concrete>
<extent>
<description>pass by reference</description>
<source_reference file="./cccc/cccc_use.cc" line="164" />
</extent>
<extent>
<description>pass by reference</description>
<source_reference file="./cccc/cccc_use.cc" line="169" />
</extent>
<name>ifstream</name>
<visible>true</visible>
<concrete>false</concrete>
<extent>
<description>pass by reference</description>
<source_reference file="./cccc/cccc_use.cc" line="206" />
</extent>
<name>ofstream</name>
<visible>true</visible>
<concrete>false</concrete>
<extent>
<description>pass by reference</description>
<source_reference file="./cccc/cccc_use.cc" line="175" />
</extent>
</supplier_module>
</module>
</structural_detail>
</CCCC_Project>
